{
    "fluentMethods": true,
    "relationships": [],
    "fields": [
        {
            "fieldName": "email",
            "fieldType": "String",
            "fieldValidateRules": [
                "required"
            ]
        },
        {
            "fieldName": "password",
            "fieldType": "String",
            "fieldValidateRules": [
                "required"
            ]
        }
    ],
    "changelogDate": "20180208093718",
    "dto": "no",
    "service": "serviceClass",
    "entityTableName": "compte_config",
    "jpaMetamodelFiltering": false,
    "pagination": "no"
}
